gola/metadata.py
gola-0.0.1.dist-info/METADATA
gola-0.0.1.dist-info/WHEEL
gola-0.0.1.dist-info/entry_points.txt
gola-0.0.1.dist-info/RECORD
