Metadata-Version: 2.3
Name: gola
Version: 0.0.1
Summary: A Static Site Generator for Technical Writing
Project-URL: Source, https://githug.com/gola-org/gola
Author-email: Jayesh Badwaik <jayesh@ambhora.com>
License-Expression: Apache-2.0
Requires-Dist: livereload
Requires-Dist: semver
